README.md
setup.cfg
setup.py
dist_gb.egg-info/PKG-INFO
dist_gb.egg-info/SOURCES.txt
dist_gb.egg-info/dependency_links.txt
dist_gb.egg-info/not-zip-safe
dist_gb.egg-info/top_level.txt
distributions/Binomialdistribution.py
distributions/Gaussiandistribution.py
distributions/Generaldistribution.py
distributions/__init__.py